ourskyai_node_platform_api/__init__.py
ourskyai_node_platform_api/api_client.py
ourskyai_node_platform_api/api_response.py
ourskyai_node_platform_api/configuration.py
ourskyai_node_platform_api/exceptions.py
ourskyai_node_platform_api/py.typed
ourskyai_node_platform_api/rest.py
ourskyai_node_platform_api/api/__init__.py
ourskyai_node_platform_api/api/default_api.py
ourskyai_node_platform_api/models/__init__.py
ourskyai_node_platform_api/models/all_sky_camera_diagnosis_report.py
ourskyai_node_platform_api/models/astro_camera_diagnosis_report.py
ourskyai_node_platform_api/models/auto_stretch_image_completed.py
ourskyai_node_platform_api/models/auto_stretch_image_started.py
ourskyai_node_platform_api/models/autofocus_failed.py
ourskyai_node_platform_api/models/autofocus_finished.py
ourskyai_node_platform_api/models/autofocus_method.py
ourskyai_node_platform_api/models/autofocus_point_added.py
ourskyai_node_platform_api/models/autofocus_started.py
ourskyai_node_platform_api/models/camera_image_captured.py
ourskyai_node_platform_api/models/camera_status.py
ourskyai_node_platform_api/models/camera_status_updated.py
ourskyai_node_platform_api/models/camera_temperature_set.py
ourskyai_node_platform_api/models/capture_image_started.py
ourskyai_node_platform_api/models/connection_status.py
ourskyai_node_platform_api/models/create_mount_model_completed.py
ourskyai_node_platform_api/models/create_mount_model_failed.py
ourskyai_node_platform_api/models/create_mount_model_started.py
ourskyai_node_platform_api/models/debug_logged.py
ourskyai_node_platform_api/models/elevation_mask_diagnostic_completed.py
ourskyai_node_platform_api/models/elevation_mask_diagnostic_failed.py
ourskyai_node_platform_api/models/elevation_mask_diagnostic_started.py
ourskyai_node_platform_api/models/elevation_mask_point_added.py
ourskyai_node_platform_api/models/empty_success.py
ourskyai_node_platform_api/models/enclosure_state.py
ourskyai_node_platform_api/models/event_type.py
ourskyai_node_platform_api-1.3.9356.dist-info/METADATA
ourskyai_node_platform_api-1.3.9356.dist-info/WHEEL
ourskyai_node_platform_api-1.3.9356.dist-info/top_level.txt
ourskyai_node_platform_api-1.3.9356.dist-info/RECORD
